oireachtas_nlp/__init__.py
oireachtas_nlp/constants.py
oireachtas_nlp/log.py
oireachtas_nlp/utils.py
oireachtas_nlp/bin/__init__.py
oireachtas_nlp/bin/belong.py
oireachtas_nlp/bin/generate_text.py
oireachtas_nlp/bin/generate_text_from_model.py
oireachtas_nlp/bin/lexical_difficulty.py
oireachtas_nlp/bin/lexical_diversity.py
oireachtas_nlp/bin/sentiment.py
oireachtas_nlp/bin/sounds_like.py
oireachtas_nlp/bin/word_usage_by.py
oireachtas_nlp/learn/__init__.py
oireachtas_nlp/learn/base_tagged_docs.py
oireachtas_nlp/learn/classifier.py
oireachtas_nlp/learn/tags.py
oireachtas_nlp/learn/utils.py
oireachtas_nlp/models/__init__.py
oireachtas_nlp/models/para.py
oireachtas_nlp/models/text.py
oireachtas_nlp/word_usage/__init__.py
oireachtas_nlp/word_usage/base_word_usage.py
oireachtas_nlp/word_usage/member_word_usage.py
oireachtas_nlp/word_usage/party_word_usage.py
oireachtas_nlp-1.0.16.dist-info/LICENSE
oireachtas_nlp-1.0.16.dist-info/METADATA
oireachtas_nlp-1.0.16.dist-info/WHEEL
oireachtas_nlp-1.0.16.dist-info/entry_points.txt
oireachtas_nlp-1.0.16.dist-info/top_level.txt
oireachtas_nlp-1.0.16.dist-info/RECORD
