Metadata-Version: 2.1
Name: oireachtas-nlp
Version: 1.0.16
Summary: nlp on data from the oireachtas api relating to members / parties
Home-page: https://github.com/RobertLucey/oireachtas-nlp
Author: Robert Lucey
Requires-Python: >=3.6
License-File: LICENSE
Requires-Dist: oireachtas-data
Requires-Dist: textstat
Requires-Dist: gensim
Requires-Dist: nltk
Requires-Dist: cached-property
Requires-Dist: sklearn-pandas
Requires-Dist: tqdm
Requires-Dist: textgenrnn
Requires-Dist: gpt-2-simple
